[
    {
        "cars": "Auto Services",
        "title": "HONDA VEZEL 2015 BEST PRICE",
        "url": "http://ikman.lk/en/ad/honda-vezel-2015-best-price-for-sale-kurunegala-10",
        "Number": "0711272771",
        "username": "Kurunegala, Kurunegala",
        "comments": "Pearl International (Pvt) Ltd MEMBER"
    },
    {
        "cars": "",
        "title": "",
        "url": "http://ikman.lk/en/ad/honda-vezel-rs-2017-2017-for-sale-kurunegala-2",
        "Number": "",
        "username": "",
        "comments": ""
    },
    {
        "cars": "",
        "title": "",
        "url": "http://ikman.lk/en/ad/three-wheeler-for-sale-gampaha-22545",
        "Number": "",
        "username": "",
        "comments": ""
    },
    {
        "cars": "",
        "title": "",
        "url": "http://ikman.lk/en/ad/tata-nano-2011-for-sale-colombo-877",
        "Number": "",
        "username": "",
        "comments": ""
    },
    {
        "cars": "",
        "title": "",
        "url": "http://ikman.lk/en/ad/bmw-320d-2000-for-sale-colombo-102",
        "Number": "",
        "username": "",
        "comments": ""
    },
    {
        "cars": "",
        "title": "",
        "url": "http://ikman.lk/en/ad/isuzu-elf-tipper-2002-for-sale-kurunegala",
        "Number": "",
        "username": "",
        "comments": ""
    },
    {
        "cars": "Cars",
        "title": "Mercedes-Benz E 200 2011",
        "url": "http://ikman.lk/en/ad/mercedes-benz-e-200-2011-for-sale-colombo-7",
        "Number": "0722969696",
        "username": "Colombo 5, Colombo",
        "comments": "S.A"
    },
    {
        "cars": "Vans, Buses & Lorries",
        "title": "Dimo Batta Lorry 2012",
        "url": "http://ikman.lk/en/ad/dimo-batta-lorry-2012-for-sale-kurunegala-2",
        "Number": "0767734661",
        "username": "Kuliyapitiya, Kurunegala",
        "comments": "Kuliyapitiya Car Sale MEMBER"
    },
    {
        "cars": "Vans, Buses & Lorries",
        "title": "Toyota kdh 201 2016",
        "url": "http://ikman.lk/en/ad/toyota-kdh-201-2016-for-sale-puttalam",
        "Number": "0775482667",
        "username": "Marawila, Puttalam",
        "comments": "Gimhan Motors"
    },
    {
        "cars": "Motorbikes & Scooters",
        "title": "Honda dio 2014",
        "url": "http://ikman.lk/en/ad/honda-dio-2014-for-sale-gampaha-2873",
        "Number": "0719127289",
        "username": "Kadawatha, Gampaha",
        "comments": "shamil"
    },
    {
        "cars": "Cars",
        "title": "Peugeot 407 (Diesel) 2008",
        "url": "http://ikman.lk/en/ad/peugeot-407-diesel-2008-for-sale-colombo",
        "Number": "0714288888",
        "username": "Colombo 5, Colombo",
        "comments": "SA"
    },
    {
        "cars": "Cars",
        "title": "Toyota Sprinter 1993",
        "url": "http://ikman.lk/en/ad/toyota-sprinter-1993-for-sale-kandy",
        "Number": "0777518658",
        "username": "Pilimatalawa, Kandy",
        "comments": "Chaminda Jayarathne"
    },
    {
        "cars": "Auto Parts & Accessories",
        "title": "full caby empty box",
        "url": "http://ikman.lk/en/ad/full-caby-empty-box-for-sale-matara",
        "Number": "0770453994",
        "username": "Hakmana, Matara",
        "comments": "supun"
    },
    {
        "cars": "Three Wheelers",
        "title": "Three Wheeler",
        "url": "http://ikman.lk/en/ad/three-wheeler-for-sale-colombo-25542",
        "Number": "0713454293",
        "username": "Piliyandala, Colombo",
        "comments": "Prasanna Kelum"
    },
    {
        "cars": "Cars",
        "title": "Toyota Allion 260 2008",
        "url": "http://ikman.lk/en/ad/toyota-allion-260-2008-for-sale-colombo-344",
        "Number": "0715329272",
        "username": "Maharagama, Colombo",
        "comments": "Sameera Guruge"
    },
    {
        "cars": "Cars",
        "title": "Perodua Axia 2015",
        "url": "http://ikman.lk/en/ad/perodua-axia-2015-for-sale-colombo-53",
        "Number": "0770048062",
        "username": "Colombo 5, Colombo",
        "comments": "Moulana"
    },
    {
        "cars": "Cars",
        "title": "Alto -800 2015",
        "url": "http://ikman.lk/en/ad/alto-800-2015-for-sale-colombo-1",
        "Number": "0777761704",
        "username": "Moratuwa, Colombo",
        "comments": "chappel"
    },
    {
        "cars": "Vans, Buses & Lorries",
        "title": "Ashok Leyland 1618 Cargo 2010",
        "url": "http://ikman.lk/en/ad/ashok-leyland-1618-cargo-2010-for-sale-puttalam",
        "Number": "0775067810",
        "username": "Wennappuwa, Puttalam",
        "comments": "Sell Fast | Kithsiri Agent MEMBER"
    },
    {
        "cars": "Auto Services",
        "title": "HONDA VEZEL RS SINSHIN 2017",
        "url": "http://ikman.lk/en/ad/honda-vezel-rs-sinshin-2017-for-sale-colombo-6",
        "Number": "0767272060",
        "username": "Colombo 10, Colombo",
        "comments": "Asiri Holdings Colombo MEMBER"
    },
    {
        "cars": "Cars",
        "title": "Nissan SUNNY N16 2000",
        "url": "http://ikman.lk/en/ad/nissan-sunny-n16-2000-for-sale-colombo-162",
        "Number": "0765742678",
        "username": "Malabe, Colombo",
        "comments": "Mahanama Car Sales MEMBER"
    },
    {
        "cars": "Vans, Buses & Lorries",
        "title": "Toyota KR42 GL White 2007",
        "url": "http://ikman.lk/en/ad/toyota-kr42-gl-white-2007-for-sale-kalutara-1",
        "Number": "0711646434",
        "username": "Kalutara, Kalutara",
        "comments": "Charitha Munirathna"
    },
    {
        "cars": "Vans, Buses & Lorries",
        "title": "Toyota coaster ex 1989",
        "url": "http://ikman.lk/en/ad/toyota-coaster-ex-1989-for-sale-gampaha-1",
        "Number": "0770546757",
        "username": "Kelaniya, Gampaha",
        "comments": "Prabo Sanju"
    },
    {
        "cars": "Cars",
        "title": "Toyota CHR HYBRID 2017",
        "url": "http://ikman.lk/en/ad/toyota-chr-hybrid-2017-for-sale-colombo-11",
        "Number": "0777694260",
        "username": "Nugegoda, Colombo",
        "comments": "Zeon International pvt ltd MEMBER"
    },
    {
        "cars": "Three Wheelers",
        "title": "Three Wheeler - 4 Stroke",
        "url": "http://ikman.lk/en/ad/three-wheeler-4-stroke-for-sale-colombo-39",
        "Number": "0770688083",
        "username": "Angoda, Colombo",
        "comments": "Asanka"
    },
    {
        "cars": "Vans, Buses & Lorries",
        "title": "Mahindra Maxsimo 2014",
        "url": "http://ikman.lk/en/ad/mahindra-maxsimo-2014-for-sale-kurunegala",
        "Number": "0775653131",
        "username": "Pannala, Kurunegala",
        "comments": "Kuliyapitiya Car Sale MEMBER"
    },
    {
        "cars": "Cars",
        "title": "Suzuki Wagon R  F 2 2015",
        "url": "http://ikman.lk/en/ad/suzuki-wagon-r-f-2-2015-for-sale-colombo",
        "Number": "0718669984",
        "username": "Nugegoda, Colombo",
        "comments": "Sell Fast | Nugegoda | Nayara Adds MEMBER"
    },
    {
        "cars": "Cars",
        "title": "Jeep 1974",
        "url": "http://ikman.lk/en/ad/jeep-1974-for-sale-galle",
        "Number": "0772775224",
        "username": "Galle, Galle",
        "comments": "Sell Fast | Galle | Inforlink Computer MEMBER"
    },
    {
        "cars": "Vans, Buses & Lorries",
        "title": "Toyota coaster ex 1989",
        "url": "http://ikman.lk/en/ad/toyota-coaster-ex-1989-for-sale-gampaha-1",
        "Number": "0770546757",
        "username": "Kelaniya, Gampaha",
        "comments": "Prabo Sanju"
    },
    {
        "cars": "Vans, Buses & Lorries",
        "title": "Toyota KR42 GL White 2007",
        "url": "http://ikman.lk/en/ad/toyota-kr42-gl-white-2007-for-sale-kalutara-1",
        "Number": "0711646434",
        "username": "Kalutara, Kalutara",
        "comments": "Charitha Munirathna"
    },
    {
        "cars": "",
        "title": "",
        "url": "http://ikman.lk/en/ad/honda-vezel-rs-2017-2017-for-sale-kurunegala-2",
        "Number": "",
        "username": "",
        "comments": ""
    },
    {
        "cars": "Auto Parts & Accessories",
        "title": "full caby empty box",
        "url": "http://ikman.lk/en/ad/full-caby-empty-box-for-sale-matara",
        "Number": "0770453994",
        "username": "Hakmana, Matara",
        "comments": "supun"
    },
    {
        "cars": "Three Wheelers",
        "title": "Three Wheeler",
        "url": "http://ikman.lk/en/ad/three-wheeler-for-sale-gampaha-22545",
        "Number": "0777551795",
        "username": "Gampaha, Gampaha",
        "comments": "Dilhan Perera MEMBER"
    },
    {
        "cars": "",
        "title": "",
        "url": "http://ikman.lk/en/ad/tata-nano-2011-for-sale-colombo-877",
        "Number": "",
        "username": "",
        "comments": ""
    },
    {
        "cars": "",
        "title": "",
        "url": "http://ikman.lk/en/ad/honda-dio-2014-for-sale-gampaha-2873",
        "Number": "",
        "username": "",
        "comments": ""
    },
    {
        "cars": "Three Wheelers",
        "title": "Three Wheeler",
        "url": "http://ikman.lk/en/ad/three-wheeler-for-sale-colombo-25542",
        "Number": "0713454293",
        "username": "Piliyandala, Colombo",
        "comments": "Prasanna Kelum"
    },
    {
        "cars": "Cars",
        "title": "Nissan SUNNY N16 2000",
        "url": "http://ikman.lk/en/ad/nissan-sunny-n16-2000-for-sale-colombo-162",
        "Number": "0765742678",
        "username": "Malabe, Colombo",
        "comments": "Mahanama Car Sales MEMBER"
    },
    {
        "cars": "Cars",
        "title": "Toyota Allion 260 2008",
        "url": "http://ikman.lk/en/ad/toyota-allion-260-2008-for-sale-colombo-344",
        "Number": "0715329272",
        "username": "Maharagama, Colombo",
        "comments": "Sameera Guruge"
    },
    {
        "cars": "Cars",
        "title": "BMW 320D 2000",
        "url": "http://ikman.lk/en/ad/bmw-320d-2000-for-sale-colombo-102",
        "Number": "0772808254",
        "username": "Colombo 5, Colombo",
        "comments": "Speed Motors (Pvt) Ltd MEMBER"
    },
    {
        "cars": "Cars",
        "title": "Mercedes-Benz E 200 2011",
        "url": "http://ikman.lk/en/ad/mercedes-benz-e-200-2011-for-sale-colombo-7",
        "Number": "0722969696",
        "username": "Colombo 5, Colombo",
        "comments": "S.A"
    },
    {
        "cars": "Vans, Buses & Lorries",
        "title": "Mahindra Maxsimo 2014",
        "url": "http://ikman.lk/en/ad/mahindra-maxsimo-2014-for-sale-kurunegala",
        "Number": "0775653131",
        "username": "Pannala, Kurunegala",
        "comments": "Kuliyapitiya Car Sale MEMBER"
    },
    {
        "cars": "Cars",
        "title": "Jeep 1974",
        "url": "http://ikman.lk/en/ad/jeep-1974-for-sale-galle",
        "Number": "0772775224",
        "username": "Galle, Galle",
        "comments": "Sell Fast | Galle | Inforlink Computer MEMBER"
    },
    {
        "cars": "Auto Services",
        "title": "HONDA VEZEL RS SINSHIN 2017",
        "url": "http://ikman.lk/en/ad/honda-vezel-rs-sinshin-2017-for-sale-colombo-6",
        "Number": "0767272060",
        "username": "Colombo 10, Colombo",
        "comments": "Asiri Holdings Colombo MEMBER"
    },
    {
        "cars": "Cars",
        "title": "Peugeot 407 (Diesel) 2008",
        "url": "http://ikman.lk/en/ad/peugeot-407-diesel-2008-for-sale-colombo",
        "Number": "0714288888",
        "username": "Colombo 5, Colombo",
        "comments": "SA"
    },
    {
        "cars": "Vans, Buses & Lorries",
        "title": "Dimo Batta Lorry 2012",
        "url": "http://ikman.lk/en/ad/dimo-batta-lorry-2012-for-sale-kurunegala-2",
        "Number": "0767734661",
        "username": "Kuliyapitiya, Kurunegala",
        "comments": "Kuliyapitiya Car Sale MEMBER"
    },
    {
        "cars": "Auto Services",
        "title": "HONDA VEZEL 2015 BEST PRICE",
        "url": "http://ikman.lk/en/ad/honda-vezel-2015-best-price-for-sale-kurunegala-10",
        "Number": "0711272771",
        "username": "Kurunegala, Kurunegala",
        "comments": "Pearl International (Pvt) Ltd MEMBER"
    },
    {
        "cars": "Cars",
        "title": "Suzuki Wagon R  F 2 2015",
        "url": "http://ikman.lk/en/ad/suzuki-wagon-r-f-2-2015-for-sale-colombo",
        "Number": "0718669984",
        "username": "Nugegoda, Colombo",
        "comments": "Sell Fast | Nugegoda | Nayara Adds MEMBER"
    },
    {
        "cars": "Vans, Buses & Lorries",
        "title": "Toyota kdh 201 2016",
        "url": "http://ikman.lk/en/ad/toyota-kdh-201-2016-for-sale-puttalam",
        "Number": "0775482667",
        "username": "Marawila, Puttalam",
        "comments": "Gimhan Motors"
    },
    {
        "cars": "Cars",
        "title": "Toyota Sprinter 1993",
        "url": "http://ikman.lk/en/ad/toyota-sprinter-1993-for-sale-kandy",
        "Number": "0777518658",
        "username": "Pilimatalawa, Kandy",
        "comments": "Chaminda Jayarathne"
    },
    {
        "cars": "Cars",
        "title": "Perodua Axia 2015",
        "url": "http://ikman.lk/en/ad/perodua-axia-2015-for-sale-colombo-53",
        "Number": "0770048062",
        "username": "Colombo 5, Colombo",
        "comments": "Moulana"
    },
    {
        "cars": "Three Wheelers",
        "title": "Three Wheeler - 4 Stroke",
        "url": "http://ikman.lk/en/ad/three-wheeler-4-stroke-for-sale-colombo-39",
        "Number": "0770688083",
        "username": "Angoda, Colombo",
        "comments": "Asanka"
    },
    {
        "cars": "Cars",
        "title": "Toyota CHR HYBRID 2017",
        "url": "http://ikman.lk/en/ad/toyota-chr-hybrid-2017-for-sale-colombo-11",
        "Number": "0777694260",
        "username": "Nugegoda, Colombo",
        "comments": "Zeon International pvt ltd MEMBER"
    },
    {
        "cars": "Vans, Buses & Lorries",
        "title": "Isuzu ELF Tipper 2002",
        "url": "http://ikman.lk/en/ad/isuzu-elf-tipper-2002-for-sale-kurunegala",
        "Number": "0777361290",
        "username": "Kurunegala, Kurunegala",
        "comments": "Ravishan Bandara"
    },
    {
        "cars": "Cars",
        "title": "Alto -800 2015",
        "url": "http://ikman.lk/en/ad/alto-800-2015-for-sale-colombo-1",
        "Number": "0777761704",
        "username": "Moratuwa, Colombo",
        "comments": "chappel"
    },
    {
        "cars": "Vans, Buses & Lorries",
        "title": "Ashok Leyland 1618 Cargo 2010",
        "url": "http://ikman.lk/en/ad/ashok-leyland-1618-cargo-2010-for-sale-puttalam",
        "Number": "0775067810",
        "username": "Wennappuwa, Puttalam",
        "comments": "Sell Fast | Kithsiri Agent MEMBER"
    },
    {
        "cars": "",
        "title": "",
        "url": "http://ikman.lk/en/ad/suzuki-wagon-r-f-2-2015-for-sale-colombo",
        "Number": "",
        "username": "",
        "comments": ""
    },
    {
        "cars": "Vans, Buses & Lorries",
        "title": "Toyota KR42 GL White 2007",
        "url": "http://ikman.lk/en/ad/toyota-kr42-gl-white-2007-for-sale-kalutara-1",
        "Number": "0711646434",
        "username": "Kalutara, Kalutara",
        "comments": "Charitha Munirathna"
    },
    {
        "cars": "Vans, Buses & Lorries",
        "title": "Toyota coaster ex 1989",
        "url": "http://ikman.lk/en/ad/toyota-coaster-ex-1989-for-sale-gampaha-1",
        "Number": "0770546757",
        "username": "Kelaniya, Gampaha",
        "comments": "Prabo Sanju"
    },
    {
        "cars": "Auto Services",
        "title": "HONDA VEZEL RS SINSHIN 2017",
        "url": "http://ikman.lk/en/ad/honda-vezel-rs-sinshin-2017-for-sale-colombo-6",
        "Number": "0767272060",
        "username": "Colombo 10, Colombo",
        "comments": "Asiri Holdings Colombo MEMBER"
    },
    {
        "cars": "Cars",
        "title": "Nissan SUNNY N16 2000",
        "url": "http://ikman.lk/en/ad/nissan-sunny-n16-2000-for-sale-colombo-162",
        "Number": "0765742678",
        "username": "Malabe, Colombo",
        "comments": "Mahanama Car Sales MEMBER"
    },
    {
        "cars": "",
        "title": "",
        "url": "http://ikman.lk/en/ad/perodua-axia-2015-for-sale-colombo-53",
        "Number": "",
        "username": "",
        "comments": ""
    },
    {
        "cars": "Cars",
        "title": "Jeep 1974",
        "url": "http://ikman.lk/en/ad/jeep-1974-for-sale-galle",
        "Number": "0772775224",
        "username": "Galle, Galle",
        "comments": "Sell Fast | Galle | Inforlink Computer MEMBER"
    },
    {
        "cars": "Cars",
        "title": "Mercedes-Benz E 200 2011",
        "url": "http://ikman.lk/en/ad/mercedes-benz-e-200-2011-for-sale-colombo-7",
        "Number": "0722969696",
        "username": "Colombo 5, Colombo",
        "comments": "S.A"
    },
    {
        "cars": "Vans, Buses & Lorries",
        "title": "Dimo Batta Lorry 2012",
        "url": "http://ikman.lk/en/ad/dimo-batta-lorry-2012-for-sale-kurunegala-2",
        "Number": "0767734661",
        "username": "Kuliyapitiya, Kurunegala",
        "comments": "Kuliyapitiya Car Sale MEMBER"
    },
    {
        "cars": "Cars",
        "title": "Toyota Sprinter 1993",
        "url": "http://ikman.lk/en/ad/toyota-sprinter-1993-for-sale-kandy",
        "Number": "0777518658",
        "username": "Pilimatalawa, Kandy",
        "comments": "Chaminda Jayarathne"
    },
    {
        "cars": "Vans, Buses & Lorries",
        "title": "Mahindra Maxsimo 2014",
        "url": "http://ikman.lk/en/ad/mahindra-maxsimo-2014-for-sale-kurunegala",
        "Number": "0775653131",
        "username": "Pannala, Kurunegala",
        "comments": "Kuliyapitiya Car Sale MEMBER"
    },
    {
        "cars": "Vans, Buses & Lorries",
        "title": "Toyota kdh 201 2016",
        "url": "http://ikman.lk/en/ad/toyota-kdh-201-2016-for-sale-puttalam",
        "Number": "0775482667",
        "username": "Marawila, Puttalam",
        "comments": "Gimhan Motors"
    },
    {
        "cars": "Cars",
        "title": "Toyota CHR HYBRID 2017",
        "url": "http://ikman.lk/en/ad/toyota-chr-hybrid-2017-for-sale-colombo-11",
        "Number": "0777694260",
        "username": "Nugegoda, Colombo",
        "comments": "Zeon International pvt ltd MEMBER"
    },
    {
        "cars": "Motorbikes & Scooters",
        "title": "Honda dio 2014",
        "url": "http://ikman.lk/en/ad/honda-dio-2014-for-sale-gampaha-2873",
        "Number": "0719127289",
        "username": "Kadawatha, Gampaha",
        "comments": "shamil"
    },
    {
        "cars": "Three Wheelers",
        "title": "Three Wheeler",
        "url": "http://ikman.lk/en/ad/three-wheeler-for-sale-colombo-25542",
        "Number": "0713454293",
        "username": "Piliyandala, Colombo",
        "comments": "Prasanna Kelum"
    },
    {
        "cars": "Auto Services",
        "title": "HONDA VEZEL 2015 BEST PRICE",
        "url": "http://ikman.lk/en/ad/honda-vezel-2015-best-price-for-sale-kurunegala-10",
        "Number": "0711272771",
        "username": "Kurunegala, Kurunegala",
        "comments": "Pearl International (Pvt) Ltd MEMBER"
    },
    {
        "cars": "Three Wheelers",
        "title": "Three Wheeler - 4 Stroke",
        "url": "http://ikman.lk/en/ad/three-wheeler-4-stroke-for-sale-colombo-39",
        "Number": "0770688083",
        "username": "Angoda, Colombo",
        "comments": "Asanka"
    },
    {
        "cars": "Three Wheelers",
        "title": "Three Wheeler",
        "url": "http://ikman.lk/en/ad/three-wheeler-for-sale-gampaha-22545",
        "Number": "0777551795",
        "username": "Gampaha, Gampaha",
        "comments": "Dilhan Perera MEMBER"
    },
    {
        "cars": "Cars",
        "title": "Tata NANO 2011",
        "url": "http://ikman.lk/en/ad/tata-nano-2011-for-sale-colombo-877",
        "Number": "0773526557",
        "username": "Dehiwala, Colombo",
        "comments": "Olympic Trade Link MEMBER"
    },
    {
        "cars": "Cars",
        "title": "Honda VEZEL RS 2017 2017",
        "url": "http://ikman.lk/en/ad/honda-vezel-rs-2017-2017-for-sale-kurunegala-2",
        "Number": "0779736068",
        "username": "Kurunegala, Kurunegala",
        "comments": "Asiri Holdings Lanka MEMBER"
    },
    {
        "cars": "Vans, Buses & Lorries",
        "title": "Ashok Leyland 1618 Cargo 2010",
        "url": "http://ikman.lk/en/ad/ashok-leyland-1618-cargo-2010-for-sale-puttalam",
        "Number": "0775067810",
        "username": "Wennappuwa, Puttalam",
        "comments": "Sell Fast | Kithsiri Agent MEMBER"
    },
    {
        "cars": "Cars",
        "title": "BMW 320D 2000",
        "url": "http://ikman.lk/en/ad/bmw-320d-2000-for-sale-colombo-102",
        "Number": "0772808254",
        "username": "Colombo 5, Colombo",
        "comments": "Speed Motors (Pvt) Ltd MEMBER"
    },
    {
        "cars": "Cars",
        "title": "Peugeot 407 (Diesel) 2008",
        "url": "http://ikman.lk/en/ad/peugeot-407-diesel-2008-for-sale-colombo",
        "Number": "0714288888",
        "username": "Colombo 5, Colombo",
        "comments": "SA"
    },
    {
        "cars": "Auto Parts & Accessories",
        "title": "full caby empty box",
        "url": "http://ikman.lk/en/ad/full-caby-empty-box-for-sale-matara",
        "Number": "0770453994",
        "username": "Hakmana, Matara",
        "comments": "supun"
    },
    {
        "cars": "Cars",
        "title": "Alto -800 2015",
        "url": "http://ikman.lk/en/ad/alto-800-2015-for-sale-colombo-1",
        "Number": "0777761704",
        "username": "Moratuwa, Colombo",
        "comments": "chappel"
    },
    {
        "cars": "Vans, Buses & Lorries",
        "title": "Isuzu ELF Tipper 2002",
        "url": "http://ikman.lk/en/ad/isuzu-elf-tipper-2002-for-sale-kurunegala",
        "Number": "0777361290",
        "username": "Kurunegala, Kurunegala",
        "comments": "Ravishan Bandara"
    },
    {
        "cars": "Cars",
        "title": "Toyota Allion 260 2008",
        "url": "http://ikman.lk/en/ad/toyota-allion-260-2008-for-sale-colombo-344",
        "Number": "0715329272",
        "username": "Maharagama, Colombo",
        "comments": "Sameera Guruge"
    },
    {
        "cars": "",
        "title": "",
        "url": "http://ikman.lk/en/ad/toyota-coaster-ex-1989-for-sale-gampaha-1",
        "Number": "",
        "username": "",
        "comments": ""
    },
    {
        "cars": "",
        "title": "",
        "url": "http://ikman.lk/en/ad/aqua-x-urban-permit-for-sale-colombo",
        "Number": "",
        "username": "",
        "comments": ""
    },
    {
        "cars": "",
        "title": "",
        "url": "http://ikman.lk/en/ad/tata-nano-2011-for-sale-colombo-877",
        "Number": "",
        "username": "",
        "comments": ""
    },
    {
        "cars": "",
        "title": "",
        "url": "http://ikman.lk/en/ad/jeep-1974-for-sale-galle",
        "Number": "",
        "username": "",
        "comments": ""
    },
    {
        "cars": "",
        "title": "",
        "url": "http://ikman.lk/en/ad/suzuki-wagon-r-f-2-2015-for-sale-colombo",
        "Number": "",
        "username": "",
        "comments": ""
    },
    {
        "cars": "",
        "title": "",
        "url": "http://ikman.lk/en/ad/three-wheeler-4-stroke-for-sale-colombo-39",
        "Number": "",
        "username": "",
        "comments": ""
    },
    {
        "cars": "",
        "title": "",
        "url": "http://ikman.lk/en/ad/honda-dio-2014-for-sale-gampaha-2873",
        "Number": "",
        "username": "",
        "comments": ""
    },
    {
        "cars": "Cars",
        "title": "Peugeot 407 (Diesel) 2008",
        "url": "http://ikman.lk/en/ad/peugeot-407-diesel-2008-for-sale-colombo",
        "Number": "0714288888",
        "username": "Colombo 5, Colombo",
        "comments": "SA"
    },
    {
        "cars": "Cars",
        "title": "Toyota Prius 2013",
        "url": "http://ikman.lk/en/ad/toyota-prius-2013-for-sale-gampaha-1026",
        "Number": "0779139138",
        "username": "Negombo, Gampaha",
        "comments": "Sell Fast | ගුණවර්ධන දැන්වීම් ආයතනය MEMBER"
    },
    {
        "cars": "Auto Services",
        "title": "TOYOTA AXIO WXB 2017",
        "url": "http://ikman.lk/en/ad/toyota-axio-wxb-2017-for-sale-colombo-36",
        "Number": "0767272060",
        "username": "Colombo 10, Colombo",
        "comments": "Asiri Holdings Colombo MEMBER"
    },
    {
        "cars": "Vans, Buses & Lorries",
        "title": "Dimo Batta Lorry 2012",
        "url": "http://ikman.lk/en/ad/dimo-batta-lorry-2012-for-sale-kurunegala-2",
        "Number": "0767734661",
        "username": "Kuliyapitiya, Kurunegala",
        "comments": "Kuliyapitiya Car Sale MEMBER"
    },
    {
        "cars": "Vans, Buses & Lorries",
        "title": "Isuzu ELF Tipper 2002",
        "url": "http://ikman.lk/en/ad/isuzu-elf-tipper-2002-for-sale-kurunegala",
        "Number": "0777361290",
        "username": "Kurunegala, Kurunegala",
        "comments": "Ravishan Bandara"
    },
    {
        "cars": "Three Wheelers",
        "title": "Three Wheeler",
        "url": "http://ikman.lk/en/ad/three-wheeler-for-sale-gampaha-22545",
        "Number": "0777551795",
        "username": "Gampaha, Gampaha",
        "comments": "Dilhan Perera MEMBER"
    },
    {
        "cars": "Cars",
        "title": "Honda VEZEL RS 2017 2017",
        "url": "http://ikman.lk/en/ad/honda-vezel-rs-2017-2017-for-sale-kurunegala-2",
        "Number": "0779736068",
        "username": "Kurunegala, Kurunegala",
        "comments": "Asiri Holdings Lanka MEMBER"
    },
    {
        "cars": "Cars",
        "title": "Perodua Axia 2015",
        "url": "http://ikman.lk/en/ad/perodua-axia-2015-for-sale-colombo-53",
        "Number": "0770048062",
        "username": "Colombo 5, Colombo",
        "comments": "Moulana"
    },
    {
        "cars": "Cars",
        "title": "Nissan SUNNY N16 2000",
        "url": "http://ikman.lk/en/ad/nissan-sunny-n16-2000-for-sale-colombo-162",
        "Number": "0765742678",
        "username": "Malabe, Colombo",
        "comments": "Mahanama Car Sales MEMBER"
    },
    {
        "cars": "Cars",
        "title": "BMW 320D 2000",
        "url": "http://ikman.lk/en/ad/bmw-320d-2000-for-sale-colombo-102",
        "Number": "0772808254",
        "username": "Colombo 5, Colombo",
        "comments": "Speed Motors (Pvt) Ltd MEMBER"
    },
    {
        "cars": "Vans, Buses & Lorries",
        "title": "Toyota kdh 201 2016",
        "url": "http://ikman.lk/en/ad/toyota-kdh-201-2016-for-sale-puttalam",
        "Number": "0775482667",
        "username": "Marawila, Puttalam",
        "comments": "Gimhan Motors"
    },
    {
        "cars": "Cars",
        "title": "Toyota Sprinter 1993",
        "url": "http://ikman.lk/en/ad/toyota-sprinter-1993-for-sale-kandy",
        "Number": "0777518658",
        "username": "Pilimatalawa, Kandy",
        "comments": "Chaminda Jayarathne"
    },
    {
        "cars": "Auto Parts & Accessories",
        "title": "full caby empty box",
        "url": "http://ikman.lk/en/ad/full-caby-empty-box-for-sale-matara",
        "Number": "0770453994",
        "username": "Hakmana, Matara",
        "comments": "supun"
    },
    {
        "cars": "Auto Services",
        "title": "HONDA VEZEL RS SINSHIN 2017",
        "url": "http://ikman.lk/en/ad/honda-vezel-rs-sinshin-2017-for-sale-colombo-6",
        "Number": "0767272060",
        "username": "Colombo 10, Colombo",
        "comments": "Asiri Holdings Colombo MEMBER"
    },
    {
        "cars": "Cars",
        "title": "Toyota Allion 260 2008",
        "url": "http://ikman.lk/en/ad/toyota-allion-260-2008-for-sale-colombo-344",
        "Number": "0715329272",
        "username": "Maharagama, Colombo",
        "comments": "Sameera Guruge"
    },
    {
        "cars": "Three Wheelers",
        "title": "Three Wheeler",
        "url": "http://ikman.lk/en/ad/three-wheeler-for-sale-colombo-25542",
        "Number": "0713454293",
        "username": "Piliyandala, Colombo",
        "comments": "Prasanna Kelum"
    },
    {
        "cars": "Vans, Buses & Lorries",
        "title": "Ashok Leyland 1618 Cargo 2010",
        "url": "http://ikman.lk/en/ad/ashok-leyland-1618-cargo-2010-for-sale-puttalam",
        "Number": "0775067810",
        "username": "Wennappuwa, Puttalam",
        "comments": "Sell Fast | Kithsiri Agent MEMBER"
    },
    {
        "cars": "Cars",
        "title": "Mercedes-Benz E 200 2011",
        "url": "http://ikman.lk/en/ad/mercedes-benz-e-200-2011-for-sale-colombo-7",
        "Number": "0722969696",
        "username": "Colombo 5, Colombo",
        "comments": "S.A"
    },
    {
        "cars": "Cars",
        "title": "Toyota CHR HYBRID 2017",
        "url": "http://ikman.lk/en/ad/toyota-chr-hybrid-2017-for-sale-colombo-11",
        "Number": "0777694260",
        "username": "Nugegoda, Colombo",
        "comments": "Zeon International pvt ltd MEMBER"
    },
    {
        "cars": "Vans, Buses & Lorries",
        "title": "Mahindra Maxsimo 2014",
        "url": "http://ikman.lk/en/ad/mahindra-maxsimo-2014-for-sale-kurunegala",
        "Number": "0775653131",
        "username": "Pannala, Kurunegala",
        "comments": "Kuliyapitiya Car Sale MEMBER"
    },
    {
        "cars": "",
        "title": "",
        "url": "http://ikman.lk/en/ad/honda-dio-2014-for-sale-gampaha-2873",
        "Number": "",
        "username": "",
        "comments": ""
    },
    {
        "cars": "",
        "title": "",
        "url": "http://ikman.lk/en/ad/jeep-1974-for-sale-galle",
        "Number": "",
        "username": "",
        "comments": ""
    },
    {
        "cars": "",
        "title": "",
        "url": "http://ikman.lk/en/ad/perodua-axia-2015-for-sale-colombo-53",
        "Number": "",
        "username": "",
        "comments": ""
    },
    {
        "cars": "",
        "title": "",
        "url": "http://ikman.lk/en/ad/toyota-chr-hybrid-2017-for-sale-colombo-11",
        "Number": "",
        "username": "",
        "comments": ""
    },
    {
        "cars": "",
        "title": "",
        "url": "http://ikman.lk/en/ad/full-caby-empty-box-for-sale-matara",
        "Number": "",
        "username": "",
        "comments": ""
    },
    {
        "cars": "",
        "title": "",
        "url": "http://ikman.lk/en/ad/toyota-kdh-201-2016-for-sale-puttalam",
        "Number": "",
        "username": "",
        "comments": ""
    },
    {
        "cars": "",
        "title": "",
        "url": "http://ikman.lk/en/ad/suzuki-wagon-r-f-2-2015-for-sale-colombo",
        "Number": "",
        "username": "",
        "comments": ""
    },
    {
        "cars": "",
        "title": "",
        "url": "http://ikman.lk/en/ad/honda-vezel-rs-sinshin-2017-for-sale-colombo-6",
        "Number": "",
        "username": "",
        "comments": ""
    },
    {
        "cars": "",
        "title": "",
        "url": "http://ikman.lk/en/ad/tata-nano-2011-for-sale-colombo-877",
        "Number": "",
        "username": "",
        "comments": ""
    },
    {
        "cars": "Vans, Buses & Lorries",
        "title": "Toyota coaster ex 1989",
        "url": "http://ikman.lk/en/ad/toyota-coaster-ex-1989-for-sale-gampaha-1",
        "Number": "0770546757",
        "username": "Kelaniya, Gampaha",
        "comments": "Prabo Sanju"
    },
    {
        "cars": "Cars",
        "title": "Mercedes-Benz E 200 2011",
        "url": "http://ikman.lk/en/ad/mercedes-benz-e-200-2011-for-sale-colombo-7",
        "Number": "0722969696",
        "username": "Colombo 5, Colombo",
        "comments": "S.A"
    },
    {
        "cars": "Auto Services",
        "title": "Aqua X Urban-Permit",
        "url": "http://ikman.lk/en/ad/aqua-x-urban-permit-for-sale-colombo",
        "Number": "0712744744",
        "username": "Colombo 3, Colombo",
        "comments": "Lalanya International MEMBER"
    },
    {
        "cars": "Vans, Buses & Lorries",
        "title": "Mahindra Maxsimo 2014",
        "url": "http://ikman.lk/en/ad/mahindra-maxsimo-2014-for-sale-kurunegala",
        "Number": "0775653131",
        "username": "Pannala, Kurunegala",
        "comments": "Kuliyapitiya Car Sale MEMBER"
    },
    {
        "cars": "Vans, Buses & Lorries",
        "title": "Ashok Leyland 1618 Cargo 2010",
        "url": "http://ikman.lk/en/ad/ashok-leyland-1618-cargo-2010-for-sale-puttalam",
        "Number": "0775067810",
        "username": "Wennappuwa, Puttalam",
        "comments": "Sell Fast | Kithsiri Agent MEMBER"
    },
    {
        "cars": "Three Wheelers",
        "title": "Three Wheeler",
        "url": "http://ikman.lk/en/ad/three-wheeler-for-sale-colombo-25542",
        "Number": "0713454293",
        "username": "Piliyandala, Colombo",
        "comments": "Prasanna Kelum"
    },
    {
        "cars": "Cars",
        "title": "Toyota Allion 260 2008",
        "url": "http://ikman.lk/en/ad/toyota-allion-260-2008-for-sale-colombo-344",
        "Number": "0715329272",
        "username": "Maharagama, Colombo",
        "comments": "Sameera Guruge"
    },
    {
        "cars": "Cars",
        "title": "BMW 320D 2000",
        "url": "http://ikman.lk/en/ad/bmw-320d-2000-for-sale-colombo-102",
        "Number": "0772808254",
        "username": "Colombo 5, Colombo",
        "comments": "Speed Motors (Pvt) Ltd MEMBER"
    },
    {
        "cars": "Auto Services",
        "title": "TOYOTA AXIO WXB 2017",
        "url": "http://ikman.lk/en/ad/toyota-axio-wxb-2017-for-sale-colombo-36",
        "Number": "0767272060",
        "username": "Colombo 10, Colombo",
        "comments": "Asiri Holdings Colombo MEMBER"
    },
    {
        "cars": "Cars",
        "title": "Toyota Sprinter 1993",
        "url": "http://ikman.lk/en/ad/toyota-sprinter-1993-for-sale-kandy",
        "Number": "0777518658",
        "username": "Pilimatalawa, Kandy",
        "comments": "Chaminda Jayarathne"
    },
    {
        "cars": "Vans, Buses & Lorries",
        "title": "Dimo Batta Lorry 2012",
        "url": "http://ikman.lk/en/ad/dimo-batta-lorry-2012-for-sale-kurunegala-2",
        "Number": "0767734661",
        "username": "Kuliyapitiya, Kurunegala",
        "comments": "Kuliyapitiya Car Sale MEMBER"
    },
    {
        "cars": "Cars",
        "title": "Peugeot 407 (Diesel) 2008",
        "url": "http://ikman.lk/en/ad/peugeot-407-diesel-2008-for-sale-colombo",
        "Number": "0714288888",
        "username": "Colombo 5, Colombo",
        "comments": "SA"
    },
    {
        "cars": "Cars",
        "title": "Honda VEZEL RS 2017 2017",
        "url": "http://ikman.lk/en/ad/honda-vezel-rs-2017-2017-for-sale-kurunegala-2",
        "Number": "0779736068",
        "username": "Kurunegala, Kurunegala",
        "comments": "Asiri Holdings Lanka MEMBER"
    },
    {
        "cars": "Cars",
        "title": "Nissan SUNNY N16 2000",
        "url": "http://ikman.lk/en/ad/nissan-sunny-n16-2000-for-sale-colombo-162",
        "Number": "0765742678",
        "username": "Malabe, Colombo",
        "comments": "Mahanama Car Sales MEMBER"
    },
    {
        "cars": "Cars",
        "title": "Toyota Prius 2013",
        "url": "http://ikman.lk/en/ad/toyota-prius-2013-for-sale-gampaha-1026",
        "Number": "0779139138",
        "username": "Negombo, Gampaha",
        "comments": "Sell Fast | ගුණවර්ධන දැන්වීම් ආයතනය MEMBER"
    },
    {
        "cars": "Vans, Buses & Lorries",
        "title": "Isuzu ELF Tipper 2002",
        "url": "http://ikman.lk/en/ad/isuzu-elf-tipper-2002-for-sale-kurunegala",
        "Number": "0777361290",
        "username": "Kurunegala, Kurunegala",
        "comments": "Ravishan Bandara"
    },
    {
        "cars": "Three Wheelers",
        "title": "Three Wheeler - 4 Stroke",
        "url": "http://ikman.lk/en/ad/three-wheeler-4-stroke-for-sale-colombo-39",
        "Number": "0770688083",
        "username": "Angoda, Colombo",
        "comments": "Asanka"
    },
    {
        "cars": "Three Wheelers",
        "title": "Three Wheeler",
        "url": "http://ikman.lk/en/ad/three-wheeler-for-sale-gampaha-22545",
        "Number": "0777551795",
        "username": "Gampaha, Gampaha",
        "comments": "Dilhan Perera MEMBER"
    },
    {
        "cars": "Three Wheelers",
        "title": "Three Wheeler",
        "url": "http://ikman.lk/en/ad/three-wheeler-for-sale-colombo-25542",
        "Number": "0713454293",
        "username": "Piliyandala, Colombo",
        "comments": "Prasanna Kelum"
    },
    {
        "cars": "Cars",
        "title": "BMW 320D 2000",
        "url": "http://ikman.lk/en/ad/bmw-320d-2000-for-sale-colombo-102",
        "Number": "0772808254",
        "username": "Colombo 5, Colombo",
        "comments": "Speed Motors (Pvt) Ltd MEMBER"
    },
    {
        "cars": "Auto Services",
        "title": "Aqua X Urban-Permit",
        "url": "http://ikman.lk/en/ad/aqua-x-urban-permit-for-sale-colombo",
        "Number": "0712744744",
        "username": "Colombo 3, Colombo",
        "comments": "Lalanya International MEMBER"
    },
    {
        "cars": "Auto Services",
        "title": "TOYOTA AXIO WXB 2017",
        "url": "http://ikman.lk/en/ad/toyota-axio-wxb-2017-for-sale-colombo-36",
        "Number": "0767272060",
        "username": "Colombo 10, Colombo",
        "comments": "Asiri Holdings Colombo MEMBER"
    },
    {
        "cars": "Cars",
        "title": "Suzuki Wagon R  F 2 2015",
        "url": "http://ikman.lk/en/ad/suzuki-wagon-r-f-2-2015-for-sale-colombo",
        "Number": "0718669984",
        "username": "Nugegoda, Colombo",
        "comments": "Sell Fast | Nugegoda | Nayara Adds MEMBER"
    },
    {
        "cars": "Cars",
        "title": "Honda VEZEL RS 2017 2017",
        "url": "http://ikman.lk/en/ad/honda-vezel-rs-2017-2017-for-sale-kurunegala-2",
        "Number": "0779736068",
        "username": "Kurunegala, Kurunegala",
        "comments": "Asiri Holdings Lanka MEMBER"
    },
    {
        "cars": "Cars",
        "title": "Perodua Axia 2015",
        "url": "http://ikman.lk/en/ad/perodua-axia-2015-for-sale-colombo-53",
        "Number": "0770048062",
        "username": "Colombo 5, Colombo",
        "comments": "Moulana"
    },
    {
        "cars": "Vans, Buses & Lorries",
        "title": "Dimo Batta Lorry 2012",
        "url": "http://ikman.lk/en/ad/dimo-batta-lorry-2012-for-sale-kurunegala-2",
        "Number": "0767734661",
        "username": "Kuliyapitiya, Kurunegala",
        "comments": "Kuliyapitiya Car Sale MEMBER"
    },
    {
        "cars": "Three Wheelers",
        "title": "Three Wheeler",
        "url": "http://ikman.lk/en/ad/three-wheeler-for-sale-gampaha-22545",
        "Number": "0777551795",
        "username": "Gampaha, Gampaha",
        "comments": "Dilhan Perera MEMBER"
    },
    {
        "cars": "Vans, Buses & Lorries",
        "title": "Mahindra Maxsimo 2014",
        "url": "http://ikman.lk/en/ad/mahindra-maxsimo-2014-for-sale-kurunegala",
        "Number": "0775653131",
        "username": "Pannala, Kurunegala",
        "comments": "Kuliyapitiya Car Sale MEMBER"
    },
    {
        "cars": "Cars",
        "title": "Jeep 1974",
        "url": "http://ikman.lk/en/ad/jeep-1974-for-sale-galle",
        "Number": "0772775224",
        "username": "Galle, Galle",
        "comments": "Sell Fast | Galle | Inforlink Computer MEMBER"
    },
    {
        "cars": "Vans, Buses & Lorries",
        "title": "Isuzu ELF Tipper 2002",
        "url": "http://ikman.lk/en/ad/isuzu-elf-tipper-2002-for-sale-kurunegala",
        "Number": "0777361290",
        "username": "Kurunegala, Kurunegala",
        "comments": "Ravishan Bandara"
    },
    {
        "cars": "Auto Services",
        "title": "HONDA VEZEL RS SINSHIN 2017",
        "url": "http://ikman.lk/en/ad/honda-vezel-rs-sinshin-2017-for-sale-colombo-6",
        "Number": "0767272060",
        "username": "Colombo 10, Colombo",
        "comments": "Asiri Holdings Colombo MEMBER"
    },
    {
        "cars": "Vans, Buses & Lorries",
        "title": "Ashok Leyland 1618 Cargo 2010",
        "url": "http://ikman.lk/en/ad/ashok-leyland-1618-cargo-2010-for-sale-puttalam",
        "Number": "0775067810",
        "username": "Wennappuwa, Puttalam",
        "comments": "Sell Fast | Kithsiri Agent MEMBER"
    },
    {
        "cars": "Auto Parts & Accessories",
        "title": "full caby empty box",
        "url": "http://ikman.lk/en/ad/full-caby-empty-box-for-sale-matara",
        "Number": "0770453994",
        "username": "Hakmana, Matara",
        "comments": "supun"
    },
    {
        "cars": "Cars",
        "title": "Nissan SUNNY N16 2000",
        "url": "http://ikman.lk/en/ad/nissan-sunny-n16-2000-for-sale-colombo-162",
        "Number": "0765742678",
        "username": "Malabe, Colombo",
        "comments": "Mahanama Car Sales MEMBER"
    },
    {
        "cars": "Cars",
        "title": "Toyota Prius 2013",
        "url": "http://ikman.lk/en/ad/toyota-prius-2013-for-sale-gampaha-1026",
        "Number": "0779139138",
        "username": "Negombo, Gampaha",
        "comments": "Sell Fast | ගුණවර්ධන දැන්වීම් ආයතනය MEMBER"
    },
    {
        "cars": "Cars",
        "title": "Peugeot 407 (Diesel) 2008",
        "url": "http://ikman.lk/en/ad/peugeot-407-diesel-2008-for-sale-colombo",
        "Number": "0714288888",
        "username": "Colombo 5, Colombo",
        "comments": "SA"
    },
    {
        "cars": "Vans, Buses & Lorries",
        "title": "Toyota kdh 201 2016",
        "url": "http://ikman.lk/en/ad/toyota-kdh-201-2016-for-sale-puttalam",
        "Number": "0775482667",
        "username": "Marawila, Puttalam",
        "comments": "Gimhan Motors"
    },
    {
        "cars": "Three Wheelers",
        "title": "Three Wheeler - 4 Stroke",
        "url": "http://ikman.lk/en/ad/three-wheeler-4-stroke-for-sale-colombo-39",
        "Number": "0770688083",
        "username": "Angoda, Colombo",
        "comments": "Asanka"
    },
    {
        "cars": "Vans, Buses & Lorries",
        "title": "Toyota coaster ex 1989",
        "url": "http://ikman.lk/en/ad/toyota-coaster-ex-1989-for-sale-gampaha-1",
        "Number": "0770546757",
        "username": "Kelaniya, Gampaha",
        "comments": "Prabo Sanju"
    },
    {
        "cars": "Cars",
        "title": "Tata NANO 2011",
        "url": "http://ikman.lk/en/ad/tata-nano-2011-for-sale-colombo-877",
        "Number": "0773526557",
        "username": "Dehiwala, Colombo",
        "comments": "Olympic Trade Link MEMBER"
    },
    {
        "cars": "Cars",
        "title": "Mercedes-Benz E 200 2011",
        "url": "http://ikman.lk/en/ad/mercedes-benz-e-200-2011-for-sale-colombo-7",
        "Number": "0722969696",
        "username": "Colombo 5, Colombo",
        "comments": "S.A"
    },
    {
        "cars": "Cars",
        "title": "Toyota CHR HYBRID 2017",
        "url": "http://ikman.lk/en/ad/toyota-chr-hybrid-2017-for-sale-colombo-11",
        "Number": "0777694260",
        "username": "Nugegoda, Colombo",
        "comments": "Zeon International pvt ltd MEMBER"
    },
    {
        "cars": "Cars",
        "title": "Toyota Sprinter 1993",
        "url": "http://ikman.lk/en/ad/toyota-sprinter-1993-for-sale-kandy",
        "Number": "0777518658",
        "username": "Pilimatalawa, Kandy",
        "comments": "Chaminda Jayarathne"
    },
    {
        "cars": "Motorbikes & Scooters",
        "title": "Honda dio 2014",
        "url": "http://ikman.lk/en/ad/honda-dio-2014-for-sale-gampaha-2873",
        "Number": "0719127289",
        "username": "Kadawatha, Gampaha",
        "comments": "shamil"
    },
    {
        "cars": "Cars",
        "title": "Toyota Allion 260 2008",
        "url": "http://ikman.lk/en/ad/toyota-allion-260-2008-for-sale-colombo-344",
        "Number": "0715329272",
        "username": "Maharagama, Colombo",
        "comments": "Sameera Guruge"
    },
    {
        "cars": "Cars",
        "title": "Tata NANO 2011",
        "url": "http://ikman.lk/en/ad/tata-nano-2011-for-sale-colombo-877",
        "Number": "0773526557",
        "username": "Dehiwala, Colombo",
        "comments": "Olympic Trade Link MEMBER"
    },
    {
        "cars": "Cars",
        "title": "Nissan FB14 1996",
        "url": "http://ikman.lk/en/ad/nissan-fb14-1996-for-sale-ratnapura-46",
        "Number": "0718216278",
        "username": "Ratnapura, Ratnapura",
        "comments": "Imal senevirathna"
    },
    {
        "cars": "Auto Parts & Accessories",
        "title": "Alto 800 Head light",
        "url": "http://ikman.lk/en/ad/alto-800-head-light-for-sale-colombo",
        "Number": "0777902180",
        "username": "Colombo 10, Colombo",
        "comments": "Don Motors MEMBER"
    },
    {
        "cars": "",
        "title": "",
        "url": "http://ikman.lk/en/ad/isuzu-elf-tipper-2002-for-sale-kurunegala",
        "Number": "",
        "username": "",
        "comments": ""
    },
    {
        "cars": "Cars",
        "title": "Nissan SUNNY N16 2000",
        "url": "http://ikman.lk/en/ad/nissan-sunny-n16-2000-for-sale-colombo-162",
        "Number": "0765742678",
        "username": "Malabe, Colombo",
        "comments": "Mahanama Car Sales MEMBER"
    },
    {
        "cars": "Cars",
        "title": "Peugeot 407 (Diesel) 2008",
        "url": "http://ikman.lk/en/ad/peugeot-407-diesel-2008-for-sale-colombo",
        "Number": "0714288888",
        "username": "Colombo 5, Colombo",
        "comments": "SA"
    },
    {
        "cars": "Heavy Machinery & Tractors",
        "title": "Excavator - komatsu - 25-1",
        "url": "http://ikman.lk/en/ad/excavator-komatsu-25-1-for-sale-kurunegala",
        "Number": "0777658553",
        "username": "Kurunegala, Kurunegala",
        "comments": "Fujimi Auto Parts (Pvt) Ltd  MEMBER"
    },
    {
        "cars": "",
        "title": "",
        "url": "http://ikman.lk/en/ad/ashok-leyland-1618-cargo-2010-for-sale-puttalam",
        "Number": "",
        "username": "",
        "comments": ""
    },
    {
        "cars": "Cars",
        "title": "Toyota Sprinter 1993",
        "url": "http://ikman.lk/en/ad/toyota-sprinter-1993-for-sale-kandy",
        "Number": "0777518658",
        "username": "Pilimatalawa, Kandy",
        "comments": "Chaminda Jayarathne"
    },
    {
        "cars": "Auto Parts & Accessories",
        "title": "full caby empty box",
        "url": "http://ikman.lk/en/ad/full-caby-empty-box-for-sale-matara",
        "Number": "0770453994",
        "username": "Hakmana, Matara",
        "comments": "supun"
    },
    {
        "cars": "Three Wheelers",
        "title": "Three Wheeler",
        "url": "http://ikman.lk/en/ad/three-wheeler-for-sale-colombo-25542",
        "Number": "0713454293",
        "username": "Piliyandala, Colombo",
        "comments": "Prasanna Kelum"
    },
    {
        "cars": "Cars",
        "title": "Toyota Allion 260 2008",
        "url": "http://ikman.lk/en/ad/toyota-allion-260-2008-for-sale-colombo-344",
        "Number": "0715329272",
        "username": "Maharagama, Colombo",
        "comments": "Sameera Guruge"
    },
    {
        "cars": "Vans, Buses & Lorries",
        "title": "Dimo Batta Lorry 2012",
        "url": "http://ikman.lk/en/ad/dimo-batta-lorry-2012-for-sale-kurunegala-2",
        "Number": "0767734661",
        "username": "Kuliyapitiya, Kurunegala",
        "comments": "Kuliyapitiya Car Sale MEMBER"
    },
    {
        "cars": "Cars",
        "title": "Toyota Prius 2013",
        "url": "http://ikman.lk/en/ad/toyota-prius-2013-for-sale-gampaha-1026",
        "Number": "0779139138",
        "username": "Negombo, Gampaha",
        "comments": "Sell Fast | ගුණවර්ධන දැන්වීම් ආයතනය MEMBER"
    },
    {
        "cars": "Cars",
        "title": "Jeep 1974",
        "url": "http://ikman.lk/en/ad/jeep-1974-for-sale-galle",
        "Number": "0772775224",
        "username": "Galle, Galle",
        "comments": "Sell Fast | Galle | Inforlink Computer MEMBER"
    },
    {
        "cars": "Three Wheelers",
        "title": "Three Wheeler",
        "url": "http://ikman.lk/en/ad/three-wheeler-for-sale-gampaha-22545",
        "Number": "0777551795",
        "username": "Gampaha, Gampaha",
        "comments": "Dilhan Perera MEMBER"
    },
    {
        "cars": "Three Wheelers",
        "title": "Three Wheeler - 4 Stroke",
        "url": "http://ikman.lk/en/ad/three-wheeler-4-stroke-for-sale-colombo-39",
        "Number": "0770688083",
        "username": "Angoda, Colombo",
        "comments": "Asanka"
    },
    {
        "cars": "Vans, Buses & Lorries",
        "title": "Mahindra Maxsimo 2014",
        "url": "http://ikman.lk/en/ad/mahindra-maxsimo-2014-for-sale-kurunegala",
        "Number": "0775653131",
        "username": "Pannala, Kurunegala",
        "comments": "Kuliyapitiya Car Sale MEMBER"
    },
    {
        "cars": "Vans, Buses & Lorries",
        "title": "Toyota kdh 201 2016",
        "url": "http://ikman.lk/en/ad/toyota-kdh-201-2016-for-sale-puttalam",
        "Number": "0775482667",
        "username": "Marawila, Puttalam",
        "comments": "Gimhan Motors"
    },
    {
        "cars": "Cars",
        "title": "Mercedes-Benz E 200 2011",
        "url": "http://ikman.lk/en/ad/mercedes-benz-e-200-2011-for-sale-colombo-7",
        "Number": "0722969696",
        "username": "Colombo 5, Colombo",
        "comments": "S.A"
    },
    {
        "cars": "Auto Services",
        "title": "HONDA VEZEL RS SINSHIN 2017",
        "url": "http://ikman.lk/en/ad/honda-vezel-rs-sinshin-2017-for-sale-colombo-6",
        "Number": "0767272060",
        "username": "Colombo 10, Colombo",
        "comments": "Asiri Holdings Colombo MEMBER"
    },
    {
        "cars": "Cars",
        "title": "Toyota axio G grade 2015",
        "url": "http://ikman.lk/en/ad/toyota-axio-g-grade-2015-for-sale-gampaha-233",
        "Number": "0772273372",
        "username": "Ragama, Gampaha",
        "comments": "T . HETTIARACHCHI"
    },
    {
        "cars": "Cars",
        "title": "Honda VEZEL RS 2017 2017",
        "url": "http://ikman.lk/en/ad/honda-vezel-rs-2017-2017-for-sale-kurunegala-2",
        "Number": "0779736068",
        "username": "Kurunegala, Kurunegala",
        "comments": "Asiri Holdings Lanka MEMBER"
    },
    {
        "cars": "Cars",
        "title": "BMW 320D 2000",
        "url": "http://ikman.lk/en/ad/bmw-320d-2000-for-sale-colombo-102",
        "Number": "0772808254",
        "username": "Colombo 5, Colombo",
        "comments": "Speed Motors (Pvt) Ltd MEMBER"
    },
    {
        "cars": "Cars",
        "title": "Perodua Axia 2015",
        "url": "http://ikman.lk/en/ad/perodua-axia-2015-for-sale-colombo-53",
        "Number": "0770048062",
        "username": "Colombo 5, Colombo",
        "comments": "Moulana"
    },
    {
        "cars": "Cars",
        "title": "Suzuki Wagon R  F 2 2015",
        "url": "http://ikman.lk/en/ad/suzuki-wagon-r-f-2-2015-for-sale-colombo",
        "Number": "0718669984",
        "username": "Nugegoda, Colombo",
        "comments": "Sell Fast | Nugegoda | Nayara Adds MEMBER"
    },
    {
        "cars": "Vans, Buses & Lorries",
        "title": "Toyota coaster ex 1989",
        "url": "http://ikman.lk/en/ad/toyota-coaster-ex-1989-for-sale-gampaha-1",
        "Number": "0770546757",
        "username": "Kelaniya, Gampaha",
        "comments": "Prabo Sanju"
    },
    {
        "cars": "",
        "title": "",
        "url": "http://ikman.lk/en/ad/ashok-leyland-1618-cargo-2010-for-sale-puttalam",
        "Number": "",
        "username": "",
        "comments": ""
    },
    {
        "cars": "Heavy Machinery & Tractors",
        "title": "Excavator - komatsu - 25-1",
        "url": "http://ikman.lk/en/ad/excavator-komatsu-25-1-for-sale-kurunegala",
        "Number": "0777658553",
        "username": "Kurunegala, Kurunegala",
        "comments": "Fujimi Auto Parts (Pvt) Ltd  MEMBER"
    },
    {
        "cars": "Vans, Buses & Lorries",
        "title": "Isuzu ELF Tipper 2002",
        "url": "http://ikman.lk/en/ad/isuzu-elf-tipper-2002-for-sale-kurunegala",
        "Number": "0777361290",
        "username": "Kurunegala, Kurunegala",
        "comments": "Ravishan Bandara"
    },
    {
        "cars": "Three Wheelers",
        "title": "Three Wheeler",
        "url": "http://ikman.lk/en/ad/three-wheeler-for-sale-colombo-25542",
        "Number": "0713454293",
        "username": "Piliyandala, Colombo",
        "comments": "Prasanna Kelum"
    },
    {
        "cars": "",
        "title": "",
        "url": "http://ikman.lk/en/ad/full-caby-empty-box-for-sale-matara",
        "Number": "",
        "username": "",
        "comments": ""
    },
    {
        "cars": "Cars",
        "title": "BMW 320D 2000",
        "url": "http://ikman.lk/en/ad/bmw-320d-2000-for-sale-colombo-102",
        "Number": "0772808254",
        "username": "Colombo 5, Colombo",
        "comments": "Speed Motors (Pvt) Ltd MEMBER"
    },
    {
        "cars": "Auto Parts & Accessories",
        "title": "Alto 800 Head light",
        "url": "http://ikman.lk/en/ad/alto-800-head-light-for-sale-colombo",
        "Number": "0777902180",
        "username": "Colombo 10, Colombo",
        "comments": "Don Motors MEMBER"
    },
    {
        "cars": "Vans, Buses & Lorries",
        "title": "Toyota coaster ex 1989",
        "url": "http://ikman.lk/en/ad/toyota-coaster-ex-1989-for-sale-gampaha-1",
        "Number": "0770546757",
        "username": "Kelaniya, Gampaha",
        "comments": "Prabo Sanju"
    },
    {
        "cars": "Vans, Buses & Lorries",
        "title": "Mahindra Maxsimo 2014",
        "url": "http://ikman.lk/en/ad/mahindra-maxsimo-2014-for-sale-kurunegala",
        "Number": "0775653131",
        "username": "Pannala, Kurunegala",
        "comments": "Kuliyapitiya Car Sale MEMBER"
    },
    {
        "cars": "Cars",
        "title": "Toyota Sprinter 1993",
        "url": "http://ikman.lk/en/ad/toyota-sprinter-1993-for-sale-kandy",
        "Number": "0777518658",
        "username": "Pilimatalawa, Kandy",
        "comments": "Chaminda Jayarathne"
    },
    {
        "cars": "Vans, Buses & Lorries",
        "title": "Dimo Batta Lorry 2012",
        "url": "http://ikman.lk/en/ad/dimo-batta-lorry-2012-for-sale-kurunegala-2",
        "Number": "0767734661",
        "username": "Kuliyapitiya, Kurunegala",
        "comments": "Kuliyapitiya Car Sale MEMBER"
    },
    {
        "cars": "Cars",
        "title": "Nissan FB14 1996",
        "url": "http://ikman.lk/en/ad/nissan-fb14-1996-for-sale-ratnapura-46",
        "Number": "0718216278",
        "username": "Ratnapura, Ratnapura",
        "comments": "Imal senevirathna"
    },
    {
        "cars": "Cars",
        "title": "Perodua Axia 2015",
        "url": "http://ikman.lk/en/ad/perodua-axia-2015-for-sale-colombo-53",
        "Number": "0770048062",
        "username": "Colombo 5, Colombo",
        "comments": "Moulana"
    },
    {
        "cars": "Cars",
        "title": "Nissan SUNNY N16 2000",
        "url": "http://ikman.lk/en/ad/nissan-sunny-n16-2000-for-sale-colombo-162",
        "Number": "0765742678",
        "username": "Malabe, Colombo",
        "comments": "Mahanama Car Sales MEMBER"
    },
    {
        "cars": "Three Wheelers",
        "title": "Three Wheeler",
        "url": "http://ikman.lk/en/ad/three-wheeler-for-sale-gampaha-22545",
        "Number": "0777551795",
        "username": "Gampaha, Gampaha",
        "comments": "Dilhan Perera MEMBER"
    },
    {
        "cars": "Cars",
        "title": "Toyota axio G grade 2015",
        "url": "http://ikman.lk/en/ad/toyota-axio-g-grade-2015-for-sale-gampaha-233",
        "Number": "0772273372",
        "username": "Ragama, Gampaha",
        "comments": "T . HETTIARACHCHI"
    },
    {
        "cars": "Three Wheelers",
        "title": "Three Wheeler - 4 Stroke",
        "url": "http://ikman.lk/en/ad/three-wheeler-4-stroke-for-sale-colombo-39",
        "Number": "0770688083",
        "username": "Angoda, Colombo",
        "comments": "Asanka"
    },
    {
        "cars": "Cars",
        "title": "Toyota Prius 2013",
        "url": "http://ikman.lk/en/ad/toyota-prius-2013-for-sale-gampaha-1026",
        "Number": "0779139138",
        "username": "Negombo, Gampaha",
        "comments": "Sell Fast | ගුණවර්ධන දැන්වීම් ආයතනය MEMBER"
    },
    {
        "cars": "Cars",
        "title": "Jeep 1974",
        "url": "http://ikman.lk/en/ad/jeep-1974-for-sale-galle",
        "Number": "0772775224",
        "username": "Galle, Galle",
        "comments": "Sell Fast | Galle | Inforlink Computer MEMBER"
    },
    {
        "cars": "Cars",
        "title": "Mercedes-Benz E 200 2011",
        "url": "http://ikman.lk/en/ad/mercedes-benz-e-200-2011-for-sale-colombo-7",
        "Number": "0722969696",
        "username": "Colombo 5, Colombo",
        "comments": "S.A"
    },
    {
        "cars": "Cars",
        "title": "Honda VEZEL RS 2017 2017",
        "url": "http://ikman.lk/en/ad/honda-vezel-rs-2017-2017-for-sale-kurunegala-2",
        "Number": "0779736068",
        "username": "Kurunegala, Kurunegala",
        "comments": "Asiri Holdings Lanka MEMBER"
    },
    {
        "cars": "Cars",
        "title": "Peugeot 407 (Diesel) 2008",
        "url": "http://ikman.lk/en/ad/peugeot-407-diesel-2008-for-sale-colombo",
        "Number": "0714288888",
        "username": "Colombo 5, Colombo",
        "comments": "SA"
    },
    {
        "cars": "Cars",
        "title": "Suzuki Wagon R  F 2 2015",
        "url": "http://ikman.lk/en/ad/suzuki-wagon-r-f-2-2015-for-sale-colombo",
        "Number": "0718669984",
        "username": "Nugegoda, Colombo",
        "comments": "Sell Fast | Nugegoda | Nayara Adds MEMBER"
    },
    {
        "cars": "Auto Services",
        "title": "HONDA VEZEL RS SINSHIN 2017",
        "url": "http://ikman.lk/en/ad/honda-vezel-rs-sinshin-2017-for-sale-colombo-6",
        "Number": "0767272060",
        "username": "Colombo 10, Colombo",
        "comments": "Asiri Holdings Colombo MEMBER"
    },
    {
        "cars": "Cars",
        "title": "Toyota Allion 260 2008",
        "url": "http://ikman.lk/en/ad/toyota-allion-260-2008-for-sale-colombo-344",
        "Number": "0715329272",
        "username": "Maharagama, Colombo",
        "comments": "Sameera Guruge"
    },
    {
        "cars": "Vans, Buses & Lorries",
        "title": "Toyota kdh 201 2016",
        "url": "http://ikman.lk/en/ad/toyota-kdh-201-2016-for-sale-puttalam",
        "Number": "0775482667",
        "username": "Marawila, Puttalam",
        "comments": "Gimhan Motors"
    },
    {
        "cars": "Cars",
        "title": "Tata NANO 2011",
        "url": "http://ikman.lk/en/ad/tata-nano-2011-for-sale-colombo-877",
        "Number": "0773526557",
        "username": "Dehiwala, Colombo",
        "comments": "Olympic Trade Link MEMBER"
    },
    {
        "cars": "Cars",
        "title": "Nissan SUNNY N16 2000",
        "url": "http://ikman.lk/en/ad/nissan-sunny-n16-2000-for-sale-colombo-162",
        "Number": "0765742678",
        "username": "Malabe, Colombo",
        "comments": "Mahanama Car Sales MEMBER"
    },
    {
        "cars": "Auto Services",
        "title": "Double Cabs Wanted On Rent",
        "url": "http://ikman.lk/en/ad/double-cabs-wanted-on-rent-to-buy-colombo",
        "Number": "0768079657",
        "username": "Colombo 3, Colombo",
        "comments": "Wanted by Travel King MEMBER"
    },
    {
        "cars": "Cars",
        "title": "Peugeot 407 (Diesel) 2008",
        "url": "http://ikman.lk/en/ad/peugeot-407-diesel-2008-for-sale-colombo",
        "Number": "0714288888",
        "username": "Colombo 5, Colombo",
        "comments": "SA"
    },
    {
        "cars": "",
        "title": "",
        "url": "http://ikman.lk/en/ad/toyota-axio-g-grade-2015-for-sale-gampaha-233",
        "Number": "",
        "username": "",
        "comments": ""
    },
    {
        "cars": "Cars",
        "title": "Toyota Prius 2013",
        "url": "http://ikman.lk/en/ad/toyota-prius-2013-for-sale-gampaha-1026",
        "Number": "0779139138",
        "username": "Negombo, Gampaha",
        "comments": "Sell Fast | ගුණවර්ධන දැන්වීම් ආයතනය MEMBER"
    },
    {
        "cars": "",
        "title": "",
        "url": "http://ikman.lk/en/ad/toyota-kdh-201-2016-for-sale-puttalam",
        "Number": "",
        "username": "",
        "comments": ""
    },
    {
        "cars": "Vans, Buses & Lorries",
        "title": "Isuzu ELF Tipper 2002",
        "url": "http://ikman.lk/en/ad/isuzu-elf-tipper-2002-for-sale-kurunegala",
        "Number": "0777361290",
        "username": "Kurunegala, Kurunegala",
        "comments": "Ravishan Bandara"
    },
    {
        "cars": "",
        "title": "",
        "url": "http://ikman.lk/en/ad/perodua-axia-2015-for-sale-colombo-53",
        "Number": "",
        "username": "",
        "comments": ""
    },
    {
        "cars": "",
        "title": "",
        "url": "http://ikman.lk/en/ad/ashok-leyland-1618-cargo-2010-for-sale-puttalam",
        "Number": "",
        "username": "",
        "comments": ""
    },
    {
        "cars": "Cars",
        "title": "Mercedes-Benz E 200 2011",
        "url": "http://ikman.lk/en/ad/mercedes-benz-e-200-2011-for-sale-colombo-7",
        "Number": "0722969696",
        "username": "Colombo 5, Colombo",
        "comments": "S.A"
    },
    {
        "cars": "Cars",
        "title": "BMW 320D 2000",
        "url": "http://ikman.lk/en/ad/bmw-320d-2000-for-sale-colombo-102",
        "Number": "0772808254",
        "username": "Colombo 5, Colombo",
        "comments": "Speed Motors (Pvt) Ltd MEMBER"
    },
    {
        "cars": "Vans, Buses & Lorries",
        "title": "Mahindra Maxsimo 2014",
        "url": "http://ikman.lk/en/ad/mahindra-maxsimo-2014-for-sale-kurunegala",
        "Number": "0775653131",
        "username": "Pannala, Kurunegala",
        "comments": "Kuliyapitiya Car Sale MEMBER"
    },
    {
        "cars": "Cars",
        "title": "Tata NANO 2011",
        "url": "http://ikman.lk/en/ad/tata-nano-2011-for-sale-colombo-877",
        "Number": "0773526557",
        "username": "Dehiwala, Colombo",
        "comments": "Olympic Trade Link MEMBER"
    },
    {
        "cars": "Three Wheelers",
        "title": "Three Wheeler",
        "url": "http://ikman.lk/en/ad/three-wheeler-for-sale-colombo-25542",
        "Number": "0713454293",
        "username": "Piliyandala, Colombo",
        "comments": "Prasanna Kelum"
    },
    {
        "cars": "Cars",
        "title": "Toyota Sprinter 1993",
        "url": "http://ikman.lk/en/ad/toyota-sprinter-1993-for-sale-kandy",
        "Number": "0777518658",
        "username": "Pilimatalawa, Kandy",
        "comments": "Chaminda Jayarathne"
    },
    {
        "cars": "Auto Parts & Accessories",
        "title": "full caby empty box",
        "url": "http://ikman.lk/en/ad/full-caby-empty-box-for-sale-matara",
        "Number": "0770453994",
        "username": "Hakmana, Matara",
        "comments": "supun"
    },
    {
        "cars": "Vans, Buses & Lorries",
        "title": "Toyota coaster ex 1989",
        "url": "http://ikman.lk/en/ad/toyota-coaster-ex-1989-for-sale-gampaha-1",
        "Number": "0770546757",
        "username": "Kelaniya, Gampaha",
        "comments": "Prabo Sanju"
    },
    {
        "cars": "Auto Services",
        "title": "HONDA VEZEL RS SINSHIN 2017",
        "url": "http://ikman.lk/en/ad/honda-vezel-rs-sinshin-2017-for-sale-colombo-6",
        "Number": "0767272060",
        "username": "Colombo 10, Colombo",
        "comments": "Asiri Holdings Colombo MEMBER"
    },
    {
        "cars": "Three Wheelers",
        "title": "Three Wheeler",
        "url": "http://ikman.lk/en/ad/three-wheeler-for-sale-gampaha-22545",
        "Number": "0777551795",
        "username": "Gampaha, Gampaha",
        "comments": "Dilhan Perera MEMBER"
    },
    {
        "cars": "Cars",
        "title": "Honda VEZEL RS 2017 2017",
        "url": "http://ikman.lk/en/ad/honda-vezel-rs-2017-2017-for-sale-kurunegala-2",
        "Number": "0779736068",
        "username": "Kurunegala, Kurunegala",
        "comments": "Asiri Holdings Lanka MEMBER"
    },
    {
        "cars": "Three Wheelers",
        "title": "Three Wheeler - 4 Stroke",
        "url": "http://ikman.lk/en/ad/three-wheeler-4-stroke-for-sale-colombo-39",
        "Number": "0770688083",
        "username": "Angoda, Colombo",
        "comments": "Asanka"
    },
    {
        "cars": "Vans, Buses & Lorries",
        "title": "Dimo Batta Lorry 2012",
        "url": "http://ikman.lk/en/ad/dimo-batta-lorry-2012-for-sale-kurunegala-2",
        "Number": "0767734661",
        "username": "Kuliyapitiya, Kurunegala",
        "comments": "Kuliyapitiya Car Sale MEMBER"
    },
    {
        "cars": "Cars",
        "title": "Nissan X TRAIL 2015",
        "url": "http://ikman.lk/en/ad/nissan-x-trail-2015-for-sale-colombo-392",
        "Number": "0773960985",
        "username": "Colombo 6, Colombo",
        "comments": "Sameera Auto Mart MEMBER"
    },
    {
        "cars": "Cars",
        "title": "Jeep 1974",
        "url": "http://ikman.lk/en/ad/jeep-1974-for-sale-galle",
        "Number": "0772775224",
        "username": "Galle, Galle",
        "comments": "Sell Fast | Galle | Inforlink Computer MEMBER"
    },
    {
        "cars": "Cars",
        "title": "Suzuki Wagon R  F 2 2015",
        "url": "http://ikman.lk/en/ad/suzuki-wagon-r-f-2-2015-for-sale-colombo",
        "Number": "0718669984",
        "username": "Nugegoda, Colombo",
        "comments": "Sell Fast | Nugegoda | Nayara Adds MEMBER"
    },
    {
        "cars": "Cars",
        "title": "Nissan FB14 1996",
        "url": "http://ikman.lk/en/ad/nissan-fb14-1996-for-sale-ratnapura-46",
        "Number": "0718216278",
        "username": "Ratnapura, Ratnapura",
        "comments": "Imal senevirathna"
    },
    {
        "cars": "Cars",
        "title": "Toyota Allion 260 2008",
        "url": "http://ikman.lk/en/ad/toyota-allion-260-2008-for-sale-colombo-344",
        "Number": "0715329272",
        "username": "Maharagama, Colombo",
        "comments": "Sameera Guruge"
    }
]